{
  "name": "Lucas Herrera",
  "age": 36,
  "address": {
    "street": "Jujful Terrace",
    "city": "Cabihjab",
    "state": "OR",
    "zip": "07638"
  },
  "contact": {
    "phone": "(244) 677-1317",
    "servicePhone": "800566765"
  },
  "birthday": "1998-06-01T07:12:17.357Z",
  "ip": "20.125.227.68",
  "foo": "bar",
  "profile": {
    "about": "Tibref id beci vupzu mah ame lumuleza ve matup ka uzov majahuke. Zu aghoroc toaho tare wojro sebzober ibzega urve atiifiren epuca patgu cap. Utnuamo ur oriuju gepfob gono vegger offecec cihulir zauj fa makad fifiw carpezne wurdamak. Zejooh demdewun noftalur mogmujer jugomwet wukad luzo sihuhdoh giam berpuz karemu anegak ema vi ri zad midin. Insobru bef mu ame sojuimi ma us ulu becif jik ac kuchewuj iti we go. Mippe racta so vena jatvuf te ewotu bud raboso tuj amikop ise ogzelu hi. Za bunowo lunafdi pilzoacu zemeslek secut ufzi wejos lihran jucofzaz jug bijemgur nek gipis wavuji ruv nimnuod fum.",
    "bio": "Vaal fade biw re uva fege tucculko ransivtaf gud osapa aki se. Hotid ramoz ticif jam fo ne cupaaku limve iz jirmel his buzihah wi labarig. Saabdoz bebawba gijocvaf gengomaz bivehhe tezufes poho obi vawe hukol zekatu vuju pamakdar unejim cavife wiove. Vow ruv dace guguk figah kuzov ti dawwezjag ven fauduvo vesi ogaove jato giocito tijwun niida as jares. At cuti webmucuc oji av bankim uzpe hathi gu parud ajuwoz liniis rorbit."
  },
  "apiKey": "7591985cc8ad5aa1c03cc35c460d7e92094d70518b81af6e5d171d2cda32b5dc",
  "currency": {
    "code": "KZT",
    "name": "Kazakhstan Tenge"
  }
}